jenkins_mcp/__init__.py
jenkins_mcp/server.py
jenkins_mcp-0.1.1.dist-info/METADATA
jenkins_mcp-0.1.1.dist-info/WHEEL
jenkins_mcp-0.1.1.dist-info/entry_points.txt
jenkins_mcp-0.1.1.dist-info/top_level.txt
jenkins_mcp-0.1.1.dist-info/RECORD
