Metadata-Version: 2.2
Name: jenkins-mcp
Version: 0.1.1
Summary: MCP server for managing Jenkins operations
Author: Kristof Jozsa
Project-URL: Repository, https://github.com/yourusername/jenkins-mcp
Requires-Python: >=3.10
Requires-Dist: fastmcp
Requires-Dist: python-jenkins
Requires-Dist: loguru
